caasclient/__init__.py
caasclient/client.py
caasclient/exceptions.py
caasclient/http.py
caasclient/shell.py
caasclient/utils.py
caasclient/v1/__init__.py
caasclient/v1/base.py
caasclient/v1/containers.py
caasclient/v1/images.py
caasclient/v1/projects.py
caasclient/v1/shell.py
caasclient-1.0.2b1.dist-info/DESCRIPTION.rst
caasclient-1.0.2b1.dist-info/METADATA
caasclient-1.0.2b1.dist-info/RECORD
caasclient-1.0.2b1.dist-info/WHEEL
caasclient-1.0.2b1.dist-info/entry_points.txt
caasclient-1.0.2b1.dist-info/metadata.json
caasclient-1.0.2b1.dist-info/top_level.txt
